material2014/__init__.py
material2014/extensions/__init__.py
material2014/extensions/tabbed.py
material2014/templates/404.html
material2014/templates/__init__.py
material2014/templates/base.html
material2014/templates/main.html
material2014/templates/mkdocs_theme.yml
material2014/templates/script.js
material2014/templates/style.css
material2014/templates/css/admonition.css
material2014/templates/css/code.css
material2014/templates/css/debug.css
material2014/templates/css/footer-nav.css
material2014/templates/css/glossary.css
material2014/templates/css/main.css
material2014/templates/css/motion.css
material2014/templates/css/navbar.css
material2014/templates/css/page-content.css
material2014/templates/css/page404.css
material2014/templates/css/search.css
material2014/templates/css/sidebar.css
material2014/templates/css/tabs.css
mkdocs_material2014-0.6.0.dist-info/licenses/LICENSE
mkdocs_material2014-0.6.0.dist-info/METADATA
mkdocs_material2014-0.6.0.dist-info/WHEEL
mkdocs_material2014-0.6.0.dist-info/entry_points.txt
mkdocs_material2014-0.6.0.dist-info/top_level.txt
mkdocs_material2014-0.6.0.dist-info/RECORD
