Metadata-Version: 2.4
Name: mkdocs-material2014
Version: 0.6.0
Summary: Documentation that simply works like it's 2014 again.
Requires-Python: >=3.12
License-File: LICENSE
Requires-Dist: mkdocs>=1.6.1
Requires-Dist: pymdown-extensions>=10.16.1
Requires-Dist: mkdocs-macros-plugin==1.3.7
Requires-Dist: pyyaml>=6.0.2
Provides-Extra: extras
Requires-Dist: mkdocs-literate-nav==0.6.2; extra == "extras"
Requires-Dist: mkdocs-ezglossary-plugin>=2.0.0; extra == "extras"
Requires-Dist: mkdocs-mermaid2-plugin>=1.2.1; extra == "extras"
Provides-Extra: openapi
Requires-Dist: essentials-openapi>=1.2.1; extra == "openapi"
Requires-Dist: rich>=14.1.0; extra == "openapi"
Requires-Dist: httpx>=0.28.1; extra == "openapi"
Requires-Dist: pyyaml; extra == "openapi"
Dynamic: license-file
